[
  {
    "text": "u cơ trơn tử cung",
    "position": [
      39,
      56
    ],
    "type": "TRIỆU_CHỨNG",
    "assertions": [
      "isHistorical"
    ],
    "candidates": []
  },
  {
    "text": "không đặc hiệu",
    "position": [
      58,
      72
    ],
    "type": "TRIỆU_CHỨNG",
    "assertions": [
      "isHistorical"
    ],
    "candidates": []
  },
  {
    "text": "iron",
    "position": [
      104,
      108
    ],
    "type": "TRIỆU_CHỨNG",
    "assertions": [
      "isHistorical"
    ],
    "candidates": []
  },
  {
    "text": "Lịch sử bệnh hiện tại",
    "position": [
      114,
      135
    ],
    "type": "CHẨN_ĐOÁN",
    "assertions": [],
    "candidates": []
  },
  {
    "text": "lower abdominal pain",
    "position": [
      228,
      248
    ],
    "type": "TRIỆU_CHỨNG",
    "assertions": [],
    "candidates": []
  },
  {
    "text": "chảy máu nhiều",
    "position": [
      255,
      269
    ],
    "type": "TRIỆU_CHỨNG",
    "assertions": [],
    "candidates": []
  },
  {
    "text": "siêu âm được thực hiện vào [Date]",
    "position": [
      312,
      345
    ],
    "type": "TRIỆU_CHỨNG",
    "assertions": [],
    "candidates": []
  },
  {
    "text": "vào thời điểm đó",
    "position": [
      373,
      389
    ],
    "type": "TRIỆU_CHỨNG",
    "assertions": [],
    "candidates": []
  },
  {
    "text": "điều trị nội khoa",
    "position": [
      451,
      468
    ],
    "type": "TRIỆU_CHỨNG",
    "assertions": [],
    "candidates": []
  },
  {
    "text": "can thiệp x-quang và điều trị ngoại khoa",
    "position": [
      470,
      510
    ],
    "type": "TRIỆU_CHỨNG",
    "assertions": [],
    "candidates": []
  },
  {
    "text": "Bệnh nhân yêu cầu cắt bỏ u xơ tử cung qua đường bụng",
    "position": [
      517,
      569
    ],
    "type": "CHẨN_ĐOÁN",
    "assertions": [
      "isFamily"
    ],
    "candidates": []
  },
  {
    "text": "siêu âm tử cung vào [Date] cho thấy",
    "position": [
      749,
      784
    ],
    "type": "TRIỆU_CHỨNG",
    "assertions": [],
    "candidates": []
  },
  {
    "text": "Tử cung đo 14",
    "position": [
      792,
      805
    ],
    "type": "TRIỆU_CHỨNG",
    "assertions": [],
    "candidates": []
  },
  {
    "text": "x 8",
    "position": [
      808,
      811
    ],
    "type": "TRIỆU_CHỨNG",
    "assertions": [
      "isHistorical"
    ],
    "candidates": []
  },
  {
    "text": "x 7",
    "position": [
      814,
      817
    ],
    "type": "TRIỆU_CHỨNG",
    "assertions": [
      "isHistorical"
    ],
    "candidates": []
  },
  {
    "text": "x 4",
    "position": [
      879,
      882
    ],
    "type": "TRIỆU_CHỨNG",
    "assertions": [
      "isHistorical"
    ],
    "candidates": []
  },
  {
    "text": "x 4",
    "position": [
      885,
      888
    ],
    "type": "TRIỆU_CHỨNG",
    "assertions": [
      "isHistorical"
    ],
    "candidates": []
  },
  {
    "text": "Không có giãn bể thận",
    "position": [
      1048,
      1069
    ],
    "type": "TRIỆU_CHỨNG",
    "assertions": [],
    "candidates": []
  }
]