[
  {
    "text": "Trước khi nhập viện",
    "position": [
      315,
      334
    ],
    "type": "TRIỆU_CHỨNG",
    "assertions": [],
    "candidates": []
  },
  {
    "text": "bệnh nhân được phát hiện trong tình trạng biến đổi ý thức",
    "position": [
      336,
      393
    ],
    "type": "CHẨN_ĐOÁN",
    "assertions": [],
    "candidates": []
  },
  {
    "text": "hạ thân nhiệt",
    "position": [
      395,
      408
    ],
    "type": "TRIỆU_CHỨNG",
    "assertions": [],
    "candidates": []
  },
  {
    "text": "biến đổi ý thức",
    "position": [
      484,
      499
    ],
    "type": "TRIỆU_CHỨNG",
    "assertions": [],
    "candidates": []
  },
  {
    "text": "hạ thân nhiệt",
    "position": [
      506,
      519
    ],
    "type": "TRIỆU_CHỨNG",
    "assertions": [],
    "candidates": []
  },
  {
    "text": "hạ huyết áp",
    "position": [
      526,
      537
    ],
    "type": "TRIỆU_CHỨNG",
    "assertions": [],
    "candidates": []
  },
  {
    "text": "đau toàn thân ít",
    "position": [
      544,
      560
    ],
    "type": "TRIỆU_CHỨNG",
    "assertions": [],
    "candidates": []
  },
  {
    "text": "đau ngực ít",
    "position": [
      567,
      578
    ],
    "type": "TRIỆU_CHỨNG",
    "assertions": [],
    "candidates": []
  },
  {
    "text": "đau bụng",
    "position": [
      586,
      594
    ],
    "type": "TRIỆU_CHỨNG",
    "assertions": [],
    "candidates": []
  },
  {
    "text": "Khám tại bệnh viện",
    "position": [
      599,
      617
    ],
    "type": "CHẨN_ĐOÁN",
    "assertions": [],
    "candidates": []
  },
  {
    "text": "Dấu hiệu lâm sàng",
    "position": [
      622,
      639
    ],
    "type": "TRIỆU_CHỨNG",
    "assertions": [],
    "candidates": []
  },
  {
    "text": "hạ huyết áp",
    "position": [
      646,
      657
    ],
    "type": "TRIỆU_CHỨNG",
    "assertions": [],
    "candidates": []
  },
  {
    "text": "hạ thân nhiệt",
    "position": [
      664,
      677
    ],
    "type": "TRIỆU_CHỨNG",
    "assertions": [],
    "candidates": []
  },
  {
    "text": "lắc đầu có/không",
    "position": [
      684,
      700
    ],
    "type": "TRIỆU_CHỨNG",
    "assertions": [],
    "candidates": []
  },
  {
    "text": "mmol/l",
    "position": [
      742,
      748
    ],
    "type": "TRIỆU_CHỨNG",
    "assertions": [],
    "candidates": []
  },
  {
    "text": "mmol/l",
    "position": [
      772,
      778
    ],
    "type": "TRIỆU_CHỨNG",
    "assertions": [],
    "candidates": []
  },
  {
    "text": "tiểu cầu là 81 G/L",
    "position": [
      785,
      803
    ],
    "type": "TRIỆU_CHỨNG",
    "assertions": [],
    "candidates": []
  },
  {
    "text": "G/L",
    "position": [
      827,
      830
    ],
    "type": "TRIỆU_CHỨNG",
    "assertions": [],
    "candidates": []
  },
  {
    "text": "tổng phân tích nước tiểu nhiễm trùng đường tiết niệu",
    "position": [
      837,
      889
    ],
    "type": "CHẨN_ĐOÁN",
    "assertions": [],
    "candidates": []
  },
  {
    "text": "Đặt sonde bàng quang",
    "position": [
      1088,
      1108
    ],
    "type": "TRIỆU_CHỨNG",
    "assertions": [],
    "candidates": []
  },
  {
    "text": "Gửi xét nghiệm máu và cấy nước tiểu",
    "position": [
      1115,
      1150
    ],
    "type": "TRIỆU_CHỨNG",
    "assertions": [],
    "candidates": []
  },
  {
    "text": "Các thủ thuậ khác",
    "position": [
      1155,
      1172
    ],
    "type": "TRIỆU_CHỨNG",
    "assertions": [],
    "candidates": []
  },
  {
    "text": "điện tâm đồ cho thấy nhịp chậm xoang",
    "position": [
      1179,
      1215
    ],
    "type": "CHẨN_ĐOÁN",
    "assertions": [],
    "candidates": []
  },
  {
    "text": "đường huyết lúc đóiđường huyết thấp)",
    "position": [
      1219,
      1255
    ],
    "type": "TRIỆU_CHỨNG",
    "assertions": [],
    "candidates": []
  }
]